{
  "sections": {
    "service_hero": {
      "type": "service-hero",
      "settings": {
        "eyebrow": "HomeBase Support Services",
        "heading": "On-Demand Home Services You Can Rely On",
        "subheading": "Snow removal, lawn care, IT support, and pet care for homeowners in Ontario.",
        "primary_label": "Request a Quote",
        "primary_link": "/pages/contact",
        "primary_new_tab": false,
        "secondary_label": "View Services",
        "secondary_link": "/collections/services",
        "secondary_new_tab": false,
        "image": "",
        "image_alt": "",
        "color_scheme": "scheme-6",
        "padding-block-start": 96,
        "padding-block-end": 96
      }
    },
    "core_services": {
      "type": "service-core-services",
      "blocks": {
        "snow": {
          "type": "service",
          "settings": {
            "title": "Snow Removal",
            "description": "Clearing driveways, walkways, and entryways with reliable response times.",
            "icon": "",
            "icon_fallback": "❄️",
            "link_label": "Learn more",
            "link": "/pages/snow-removal",
            "link_new_tab": false,
            "color_scheme": "scheme-2"
          }
        },
        "lawn": {
          "type": "service",
          "settings": {
            "title": "Lawn Care",
            "description": "Grass cutting, leaf collection, and seasonal cleanups to keep your yard ready.",
            "icon": "",
            "icon_fallback": "🌿",
            "link_label": "Learn more",
            "link": "/pages/lawn-care",
            "link_new_tab": false,
            "color_scheme": "scheme-2"
          }
        },
        "it": {
          "type": "service",
          "settings": {
            "title": "IT Support",
            "description": "Setup, troubleshooting, and consulting for your home technology.",
            "icon": "",
            "icon_fallback": "💻",
            "link_label": "Learn more",
            "link": "/pages/it-support",
            "link_new_tab": false,
            "color_scheme": "scheme-2"
          }
        },
        "pet": {
          "type": "service",
          "settings": {
            "title": "Pet Care",
            "description": "Dog walking and pet check-ins with caring, reliable helpers.",
            "icon": "",
            "icon_fallback": "🐾",
            "link_label": "Learn more",
            "link": "/pages/pet-care",
            "link_new_tab": false,
            "color_scheme": "scheme-2"
          }
        }
      },
      "block_order": [
        "snow",
        "lawn",
        "it",
        "pet"
      ],
      "settings": {
        "heading": "Core Services",
        "subheading": "Snow Removal, Lawn Care, IT Support, and Pet Care tailored for homeowners.",
        "color_scheme": "scheme-1",
        "padding-block-start": 84,
        "padding-block-end": 84
      }
    },
    "steps": {
      "type": "service-how-it-works",
      "blocks": {
        "step1": {
          "type": "step",
          "settings": {
            "title": "Request",
            "description": "Share the service, address, and timing you prefer.",
            "color_scheme": "scheme-2"
          }
        },
        "step2": {
          "type": "step",
          "settings": {
            "title": "We confirm",
            "description": "We review the request, confirm details, and schedule your visit.",
            "color_scheme": "scheme-2"
          }
        },
        "step3": {
          "type": "step",
          "settings": {
            "title": "Service performed",
            "description": "Our team completes the job and ensures you’re satisfied.",
            "color_scheme": "scheme-2"
          }
        }
      },
      "block_order": [
        "step1",
        "step2",
        "step3"
      ],
      "settings": {
        "heading": "How it works",
        "subheading": "Simple, transparent steps for every service request.",
        "color_scheme": "scheme-1",
        "padding-block-start": 80,
        "padding-block-end": 80
      }
    },
    "testimonials": {
      "type": "service-testimonials",
      "blocks": {
        "t1": {
          "type": "testimonial",
          "settings": {
            "quote": "They cleared our driveway fast and kept us updated the whole time.",
            "name": "Alex, Ontario",
            "location": "Snow Removal",
            "color_scheme": "scheme-2"
          }
        },
        "t2": {
          "type": "testimonial",
          "settings": {
            "quote": "Great lawn care crew—on time and detail-oriented.",
            "name": "Priya, Burlington",
            "location": "Lawn Care",
            "color_scheme": "scheme-2"
          }
        },
        "t3": {
          "type": "testimonial",
          "settings": {
            "quote": "Quickly fixed our Wi-Fi and set up the new router.",
            "name": "Jamie, Oakville",
            "location": "IT Support",
            "color_scheme": "scheme-2"
          }
        }
      },
      "block_order": [
        "t1",
        "t2",
        "t3"
      ],
      "settings": {
        "heading": "Trusted by homeowners",
        "subheading": "Responsive, trustworthy service for snow, lawn, IT, and pet care.",
        "service_area": "Serving homeowners across Ontario, Canada.",
        "color_scheme": "scheme-1",
        "padding-block-start": 80,
        "padding-block-end": 80
      }
    }
  },
  "order": [
    "service_hero",
    "core_services",
    "steps",
    "testimonials"
  ]
}
